pythreads/__about__.py
pythreads/__init__.py
pythreads/api.py
pythreads/configuration.py
pythreads/credentials.py
pythreads/threads.py
pythreads-0.2.0.dist-info/METADATA
pythreads-0.2.0.dist-info/WHEEL
pythreads-0.2.0.dist-info/licenses/LICENSE.txt
pythreads-0.2.0.dist-info/RECORD
