Metadata-Version: 2.3
Name: pythreads
Version: 0.2.0
Summary: A Python wrapper of Meta's Threads API
Project-URL: Homepage, https://github.com/marclove/pythreads
Project-URL: Documentation, https://github.com/marclove/pythreads#readme
Project-URL: Repository, https://github.com/marclove/pythreads
Project-URL: Issues, https://github.com/marclove/pythreads/issues
Author-email: Marc Love <copyright@marclove.com>
Maintainer-email: Marc Love <copyright@marclove.com>
License: MIT License
License-File: LICENSE.txt
Keywords: meta,sdk,threads
Classifier: Development Status :: 4 - Beta
Classifier: Intended Audience :: Developers
Classifier: License :: OSI Approved :: MIT License
Classifier: Programming Language :: Python
Classifier: Programming Language :: Python :: 3.8
Classifier: Programming Language :: Python :: 3.9
Classifier: Programming Language :: Python :: 3.10
Classifier: Programming Language :: Python :: 3.11
Classifier: Programming Language :: Python :: 3.12
Classifier: Programming Language :: Python :: Implementation :: CPython
Classifier: Programming Language :: Python :: Implementation :: PyPy
Classifier: Topic :: Software Development :: Libraries
Classifier: Topic :: Software Development :: Libraries :: Python Modules
Requires-Python: >=3.8
Requires-Dist: aiohttp==3.9.*
Requires-Dist: python-dotenv==1.0.*
Requires-Dist: requests-oauthlib==2.0.*
Requires-Dist: requests==2.32.*
